[{"line":1,"elements":[{"start_timestamp":"2024-04-15T21:05:05.122Z","before":[{"result":{"duration":4015400,"status":"passed"},"match":{"location":"StepDefinitions.Hooks.Before()"}}],"line":3,"name":"Validate Movies are sorted by Ascending alphabetical order","description":"","id":"display-and-select-star-wars-movies;validate-movies-are-sorted-by-ascending-alphabetical-order","after":[{"result":{"duration":128648200,"status":"passed"},"match":{"location":"StepDefinitions.Hooks.Cleanup()"}}],"type":"scenario","keyword":"Scenario","steps":[{"result":{"duration":1368357700,"status":"passed"},"line":4,"name":"I launch browser","match":{"location":"StepDefinitions.HomePageSteps.iLaunchBrowser()"},"keyword":"Given "},{"result":{"duration":1088497700,"status":"passed"},"line":5,"name":"I navigate to home","match":{"location":"StepDefinitions.HomePageSteps.iNavigateToHome()"},"keyword":"And "},{"result":{"duration":49430300,"status":"passed"},"line":6,"name":"I click the \"Title\"","match":{"arguments":[{"val":"\"Title\"","offset":12}],"location":"StepDefinitions.HomePageSteps.iClickThe(java.lang.String)"},"keyword":"When "},{"result":{"duration":121429300,"status":"passed"},"line":7,"name":"I validate the last movie is \"The Phantom Menace\"","match":{"arguments":[{"val":"\"The Phantom Menace\"","offset":29}],"location":"StepDefinitions.HomePageSteps.iValidateTheLastMovieIs(java.lang.String)"},"keyword":"Then "}]},{"start_timestamp":"2024-04-15T21:05:07.898Z","before":[{"result":{"status":"passed"},"match":{"location":"StepDefinitions.Hooks.Before()"}}],"line":9,"name":"Validate The The Phantom Menace movie Planets list has Camino","description":"","id":"display-and-select-star-wars-movies;validate-the-the-phantom-menace-movie-planets-list-has-camino","after":[{"result":{"duration":134687900,"status":"passed"},"match":{"location":"StepDefinitions.Hooks.Cleanup()"}}],"type":"scenario","keyword":"Scenario","steps":[{"result":{"duration":970515400,"status":"passed"},"line":10,"name":"I launch browser","match":{"location":"StepDefinitions.HomePageSteps.iLaunchBrowser()"},"keyword":"Given "},{"result":{"duration":1052305700,"status":"passed"},"line":11,"name":"I navigate to home","match":{"location":"StepDefinitions.HomePageSteps.iNavigateToHome()"},"keyword":"And "},{"result":{"duration":80622900,"status":"passed"},"line":12,"name":"I click the required movie \"The Phantom Menace\"","match":{"arguments":[{"val":"\"The Phantom Menace\"","offset":27}],"location":"StepDefinitions.HomePageSteps.iClickTheRequiredMovie(java.lang.String)"},"keyword":"And "},{"result":{"duration":1590807600,"status":"passed"},"line":13,"name":"I validate if Planets section list has \"Camino\"","match":{"arguments":[{"val":"\"Camino\"","offset":39}],"location":"StepDefinitions.HomePageSteps.iValidateIfPlanetsSectionListHas(java.lang.String)"},"keyword":"And "}]},{"start_timestamp":"2024-04-15T21:05:11.729Z","before":[{"result":{"status":"passed"},"match":{"location":"StepDefinitions.Hooks.Before()"}}],"line":15,"name":"Validate The Empire Strikes Back movie Species list has Wookie","description":"","id":"display-and-select-star-wars-movies;validate-the-empire-strikes-back-movie-species-list-has-wookie","after":[{"result":{"duration":125703400,"status":"passed"},"match":{"location":"StepDefinitions.Hooks.Cleanup()"}}],"type":"scenario","keyword":"Scenario","steps":[{"result":{"duration":959621400,"status":"passed"},"line":16,"name":"I launch browser","match":{"location":"StepDefinitions.HomePageSteps.iLaunchBrowser()"},"keyword":"Given "},{"result":{"duration":1086691500,"status":"passed"},"line":17,"name":"I navigate to home","match":{"location":"StepDefinitions.HomePageSteps.iNavigateToHome()"},"keyword":"And "},{"result":{"duration":73562200,"status":"passed"},"line":18,"name":"I click the required movie \"The Empire Strikes Back\"","match":{"arguments":[{"val":"\"The Empire Strikes Back\"","offset":27}],"location":"StepDefinitions.HomePageSteps.iClickTheRequiredMovie(java.lang.String)"},"keyword":"And "},{"result":{"error_message":"java.lang.AssertionError\r\n\tat org.junit.Assert.fail(Assert.java:87)\r\n\tat StepDefinitions.HomePageSteps.iValidateIfSpeciesSectionListHas(HomePageSteps.java:79)\r\n\tat ✽.I validate if Species section list has \"Wookie\"(file:///C:/Users/siphamandla.marenene/Desktop/DigiCertAssessment/src/test/resources/Features/HomePage.feature:19)\r\n","duration":11652300,"status":"failed"},"line":19,"name":"I validate if Species section list has \"Wookie\"","match":{"arguments":[{"val":"\"Wookie\"","offset":39}],"location":"StepDefinitions.HomePageSteps.iValidateIfSpeciesSectionListHas(java.lang.String)"},"keyword":"Then "}]}],"name":"Display and Select Star Wars Movies","description":"","id":"display-and-select-star-wars-movies","keyword":"Feature","uri":"file:src/test/resources/Features/HomePage.feature","tags":[]}]